librarios/__init__.py
librarios/funcs.py
librarios/main.py
librarios-0.6.dist-info/METADATA
librarios-0.6.dist-info/WHEEL
librarios-0.6.dist-info/entry_points.txt
librarios-0.6.dist-info/top_level.txt
librarios-0.6.dist-info/RECORD
